cse_lk/__init__.py
cse_lk/client.py
cse_lk/exceptions.py
cse_lk/models.py
cse_lk-1.0.0.dist-info/licenses/LICENSE
tests/__init__.py
tests/test_client.py
tests/test_models.py
cse_lk-1.0.0.dist-info/METADATA
cse_lk-1.0.0.dist-info/WHEEL
cse_lk-1.0.0.dist-info/top_level.txt
cse_lk-1.0.0.dist-info/RECORD
